ml_adapter/torch/__init__.py
ml_adapter/torch/adapter.py
ml_adapter/torch/marshall.py
ml_adapter/torch/py.typed
waylay_ml_adapter_torch-0.1.1.dist-info/licenses/LICENCE.txt
waylay_ml_adapter_torch-0.1.1.dist-info/METADATA
waylay_ml_adapter_torch-0.1.1.dist-info/WHEEL
waylay_ml_adapter_torch-0.1.1.dist-info/top_level.txt
waylay_ml_adapter_torch-0.1.1.dist-info/RECORD
