Metadata-Version: 2.4
Name: waylay-ml-adapter-torch
Version: 0.1.1
Summary: ML_adapter for torch.
Author-email: Waylay <info@waylay.io>
Requires-Python: >=3.11
License-File: LICENCE.txt
Requires-Dist: waylay-ml-adapter-api
Requires-Dist: waylay-ml-adapter-base
Requires-Dist: waylay-ml-adapter-numpy
Provides-Extra: torch
Requires-Dist: torch; extra == "torch"
Provides-Extra: torchvision
Requires-Dist: torch; extra == "torchvision"
Requires-Dist: torchvision; extra == "torchvision"
Provides-Extra: torchaudio
Requires-Dist: torch; extra == "torchaudio"
Requires-Dist: torchaudio; extra == "torchaudio"
Provides-Extra: dev
Requires-Dist: waylay-ml-adapter-devtools; extra == "dev"
Requires-Dist: torch; extra == "dev"
Requires-Dist: torchaudio; extra == "dev"
Requires-Dist: soundfile; extra == "dev"
Requires-Dist: deep_phonemizer; extra == "dev"
Dynamic: license-file
